PygameToolsBox/__init__.py
PygameToolsBox/animated_object.py
PygameToolsBox/button.py
PygameToolsBox/mask_image.py
PygameToolsBox/parallax_bg.py
PygameToolsBox/spritesheet.py
PygameToolsBox-1.2.2.dist-info/LICENSE
PygameToolsBox-1.2.2.dist-info/METADATA
PygameToolsBox-1.2.2.dist-info/WHEEL
PygameToolsBox-1.2.2.dist-info/top_level.txt
PygameToolsBox-1.2.2.dist-info/RECORD
