Metadata-Version: 2.1
Name: PygameToolsBox
Version: 1.2.2
Summary: Library for manage sprite sheet, and pallax background
Author-email: FranckSix <francksix@gmail.com>
License: MIT
Project-URL: Homepage, https://github.com/FranckSix/PygameSpriteTools
Project-URL: Issues, https://github.com/FranckSix/PygameSpriteTools/issues
Classifier: Programming Language :: Python :: 3
Classifier: License :: OSI Approved :: MIT License
Classifier: Operating System :: OS Independent
Requires-Python: >=3.10
License-File: LICENSE
Requires-Dist: pygame >=2.5.0
